heliq/__init__.py
heliq/alignment.py
heliq/cylindrical.py
heliq/helicity.py
heliq/version.py
heliq-1.1.1.dist-info/LICENSE
heliq-1.1.1.dist-info/METADATA
heliq-1.1.1.dist-info/WHEEL
heliq-1.1.1.dist-info/top_level.txt
heliq-1.1.1.dist-info/RECORD
