Metadata-Version: 2.1
Name: heliq
Version: 1.1.1
Summary: Quantification of helical morphologies
Home-page: https://github.com/wohe157/heliq
Author: Wouter Heyvaert
Author-email: wouter.heyvaert@student.uantwerpen.be
License: MIT
Platform: any
Classifier: Programming Language :: Python :: 3
Classifier: License :: OSI Approved :: MIT License
Classifier: Operating System :: OS Independent
Requires-Python: >=3.7
License-File: LICENSE
Requires-Dist: numpy
Requires-Dist: scipy
Requires-Dist: matplotlib
